<ArrayOfStorageLayer xmlns:i="http://www.w3.org/2001/XMLSchema-instance" z:Id="i1" xmlns:z="http://schemas.microsoft.com/2003/10/Serialization/" xmlns="http://schemas.datacontract.org/2004/07/Tychaia.ProceduralGeneration"><StorageLayer z:Id="i2"><EditorX>-5686</EditorX><EditorY>320</EditorY><m_Algorithm i:type="AlgorithmInitialBool" z:Id="i3"><ColorSet>Land</ColorSet><GuaranteeStartingPoint>true</GuaranteeStartingPoint><HigherValue>1</HigherValue><Layer2D>true</Layer2D><Limit>0.95</Limit><LowerValue>-1</LowerValue></m_Algorithm><m_Layers z:Id="i4" /></StorageLayer><StorageLayer z:Id="i5"><EditorX>-5444</EditorX><EditorY>319</EditorY><m_Algorithm i:type="AlgorithmZoom2D" z:Id="i6"><Mode>Fuzzy</Mode></m_Algorithm><m_Layers z:Id="i7"><StorageLayer z:Ref="i2" /></m_Layers></StorageLayer><StorageLayer z:Id="i8"><EditorX>-4950</EditorX><EditorY>318</EditorY><m_Algorithm i:type="AlgorithmZoom2D" z:Id="i9"><Mode>Smooth</Mode></m_Algorithm><m_Layers z:Id="i10"><StorageLayer z:Id="i11"><EditorX>-5200</EditorX><EditorY>318</EditorY><m_Algorithm i:type="AlgorithmIncrementWaterDistance" z:Id="i12"><ColorSet>Land</ColorSet><Initial>false</Initial><MaxTerrainBinary>1</MaxTerrainBinary></m_Algorithm><m_Layers z:Id="i13"><StorageLayer z:Ref="i5" /></m_Layers></StorageLayer></m_Layers></StorageLayer><StorageLayer z:Id="i14"><EditorX>-4456</EditorX><EditorY>318</EditorY><m_Algorithm i:type="AlgorithmZoom2D" z:Id="i15"><Mode>Smooth</Mode></m_Algorithm><m_Layers z:Id="i16"><StorageLayer z:Id="i17"><EditorX>-4706</EditorX><EditorY>318</EditorY><m_Algorithm i:type="AlgorithmIncrementWaterDistance" z:Id="i18"><ColorSet>Land</ColorSet><Initial>false</Initial><MaxTerrainBinary>2</MaxTerrainBinary></m_Algorithm><m_Layers z:Id="i19"><StorageLayer z:Ref="i8" /></m_Layers></StorageLayer></m_Layers></StorageLayer><StorageLayer z:Ref="i11" /><StorageLayer z:Ref="i17" /><StorageLayer z:Id="i20"><EditorX>-3955</EditorX><EditorY>320</EditorY><m_Algorithm i:type="AlgorithmZoom2D" z:Id="i21"><Mode>Smooth</Mode></m_Algorithm><m_Layers z:Id="i22"><StorageLayer z:Id="i23"><EditorX>-4201</EditorX><EditorY>318</EditorY><m_Algorithm i:type="AlgorithmIncrementWaterDistance" z:Id="i24"><ColorSet>Land</ColorSet><Initial>false</Initial><MaxTerrainBinary>3</MaxTerrainBinary></m_Algorithm><m_Layers z:Id="i25"><StorageLayer z:Ref="i14" /></m_Layers></StorageLayer></m_Layers></StorageLayer><StorageLayer z:Ref="i23" /><StorageLayer z:Id="i26"><EditorX>-3709</EditorX><EditorY>321</EditorY><m_Algorithm i:type="AlgorithmIncrementWaterDistance" z:Id="i27"><ColorSet>Land</ColorSet><Initial>false</Initial><MaxTerrainBinary>4</MaxTerrainBinary></m_Algorithm><m_Layers z:Id="i28"><StorageLayer z:Ref="i20" /></m_Layers></StorageLayer><StorageLayer z:Id="i29"><EditorX>-3459</EditorX><EditorY>322</EditorY><m_Algorithm i:type="AlgorithmZoom2D" z:Id="i30"><Mode>SmoothSpread</Mode></m_Algorithm><m_Layers z:Id="i31"><StorageLayer z:Ref="i26" /></m_Layers></StorageLayer><StorageLayer z:Id="i32"><EditorX>-2924</EditorX><EditorY>324</EditorY><m_Algorithm i:type="AlgorithmIncrementWaterDistance" z:Id="i33"><ColorSet>Land</ColorSet><Initial>false</Initial><MaxTerrainBinary>5</MaxTerrainBinary></m_Algorithm><m_Layers z:Id="i34"><StorageLayer z:Id="i35"><EditorX>-3168</EditorX><EditorY>324</EditorY><m_Algorithm i:type="AlgorithmNormalizeHeight" z:Id="i36" /><m_Layers z:Id="i37"><StorageLayer z:Ref="i29" /></m_Layers></StorageLayer></m_Layers></StorageLayer><StorageLayer z:Id="i38"><EditorX>-2432</EditorX><EditorY>323</EditorY><m_Algorithm i:type="AlgorithmIncrementWaterDistance" z:Id="i39"><ColorSet>Land</ColorSet><Initial>false</Initial><MaxTerrainBinary>6</MaxTerrainBinary></m_Algorithm><m_Layers z:Id="i40"><StorageLayer z:Id="i41"><EditorX>-2678</EditorX><EditorY>325</EditorY><m_Algorithm i:type="AlgorithmZoom2D" z:Id="i42"><Mode>Smooth</Mode></m_Algorithm><m_Layers z:Id="i43"><StorageLayer z:Ref="i32" /></m_Layers></StorageLayer></m_Layers></StorageLayer><StorageLayer z:Id="i44"><EditorX>727</EditorX><EditorY>96</EditorY><m_Algorithm i:type="AlgorithmGenerateBlockInfo" z:Id="i45"><Layer2D>false</Layer2D></m_Algorithm><m_Layers z:Id="i46"><StorageLayer z:Id="i47"><EditorX>318</EditorX><EditorY>90</EditorY><m_Algorithm i:type="AlgorithmValueTo3D" z:Id="i48"><ColorSet>Land</ColorSet><EstimateMax>64</EstimateMax></m_Algorithm><m_Layers z:Id="i49"><StorageLayer z:Id="i50"><EditorX>161</EditorX><EditorY>325</EditorY><m_Algorithm i:type="AlgorithmRemoveSinglePoints" z:Id="i51" /><m_Layers z:Id="i52"><StorageLayer z:Id="i53"><EditorX>-95</EditorX><EditorY>325</EditorY><m_Algorithm i:type="AlgorithmRemoveSinglePoints" z:Id="i54" /><m_Layers z:Id="i55"><StorageLayer z:Id="i56"><EditorX>-349</EditorX><EditorY>324</EditorY><m_Algorithm i:type="AlgorithmSlopeHeight" z:Id="i57" /><m_Layers z:Id="i58"><StorageLayer z:Id="i59"><EditorX>-627</EditorX><EditorY>323</EditorY><m_Algorithm i:type="AlgorithmRemoveSinglePoints" z:Id="i60" /><m_Layers z:Id="i61"><StorageLayer z:Id="i62"><EditorX>-882</EditorX><EditorY>323</EditorY><m_Algorithm i:type="AlgorithmNormalizeHeight" z:Id="i63" /><m_Layers z:Id="i64"><StorageLayer z:Id="i65"><EditorX>-1163</EditorX><EditorY>322</EditorY><m_Algorithm i:type="AlgorithmRemoveSinglePoints" z:Id="i66" /><m_Layers z:Id="i67"><StorageLayer z:Id="i68"><EditorX>-1421</EditorX><EditorY>322</EditorY><m_Algorithm i:type="AlgorithmNormalizeHeight" z:Id="i69" /><m_Layers z:Id="i70"><StorageLayer z:Id="i71"><EditorX>-1701</EditorX><EditorY>322</EditorY><m_Algorithm i:type="AlgorithmZoom2D" z:Id="i72"><Mode>Smooth</Mode></m_Algorithm><m_Layers z:Id="i73"><StorageLayer z:Id="i74"><EditorX>-1942</EditorX><EditorY>322</EditorY><m_Algorithm i:type="AlgorithmZoom2D" z:Id="i75"><Mode>Smooth</Mode></m_Algorithm><m_Layers z:Id="i76"><StorageLayer z:Id="i77"><EditorX>-2186</EditorX><EditorY>322</EditorY><m_Algorithm i:type="AlgorithmZoom2D" z:Id="i78"><Mode>Smooth</Mode></m_Algorithm><m_Layers z:Id="i79"><StorageLayer z:Ref="i38" /></m_Layers></StorageLayer></m_Layers></StorageLayer></m_Layers></StorageLayer></m_Layers></StorageLayer></m_Layers></StorageLayer></m_Layers></StorageLayer></m_Layers></StorageLayer></m_Layers></StorageLayer></m_Layers></StorageLayer></m_Layers></StorageLayer></m_Layers></StorageLayer></m_Layers></StorageLayer><StorageLayer z:Ref="i47" /><StorageLayer z:Id="i80"><EditorX>719</EditorX><EditorY>362</EditorY><m_Algorithm i:type="AlgorithmEdgeDetection" z:Id="i81" /><m_Layers z:Id="i82"><StorageLayer z:Ref="i47" /></m_Layers></StorageLayer><StorageLayer z:Ref="i71" /><StorageLayer z:Ref="i74" /><StorageLayer z:Ref="i77" /><StorageLayer z:Ref="i65" /><StorageLayer z:Ref="i59" /><StorageLayer z:Ref="i62" /><StorageLayer z:Ref="i68" /><StorageLayer z:Ref="i50" /><StorageLayer z:Ref="i53" /><StorageLayer z:Ref="i35" /><StorageLayer z:Ref="i56" /><StorageLayer z:Ref="i41" /><StorageLayer z:Id="i83"><EditorX>-3479</EditorX><EditorY>59</EditorY><m_Algorithm i:type="AlgorithmAdd" z:Id="i84"><EstimateMax>20</EstimateMax><Layer2d>true</Layer2d></m_Algorithm><m_Layers z:Id="i85"><StorageLayer z:Ref="i14" /><StorageLayer z:Ref="i38" /></m_Layers></StorageLayer><StorageLayer z:Id="i86"><EditorX>85</EditorX><EditorY>649</EditorY><m_Algorithm i:type="AlgorithmInitialBeings" z:Id="i87"><GuaranteeStartingPoint>true</GuaranteeStartingPoint><Limit>0.9</Limit><PlacementType>Enemies</PlacementType></m_Algorithm><m_Layers z:Id="i88"><StorageLayer z:Id="i89"><EditorX>-188</EditorX><EditorY>649</EditorY><m_Algorithm i:type="AlgorithmConstant" z:Id="i90"><Color xmlns:d6p1="http://schemas.datacontract.org/2004/07/System.Drawing"><d6p1:knownColor>0</d6p1:knownColor><d6p1:name i:nil="true" /><d6p1:state>0</d6p1:state><d6p1:value>0</d6p1:value></Color><Constant>0</Constant><Layer2D>true</Layer2D></m_Algorithm><m_Layers z:Id="i91" /></StorageLayer></m_Layers></StorageLayer><StorageLayer z:Ref="i89" /><StorageLayer z:Id="i92"><EditorX>327</EditorX><EditorY>649</EditorY><m_Algorithm i:type="AlgorithmBeingsZoom2D" z:Id="i93"><Mode>Spread</Mode></m_Algorithm><m_Layers z:Id="i94"><StorageLayer z:Ref="i86" /></m_Layers></StorageLayer><StorageLayer z:Id="i95"><EditorX>573</EditorX><EditorY>649</EditorY><m_Algorithm i:type="AlgorithmBeingsZoom2D" z:Id="i96"><Mode>Spread</Mode></m_Algorithm><m_Layers z:Id="i97"><StorageLayer z:Ref="i92" /></m_Layers></StorageLayer><StorageLayer z:Id="i98"><EditorX>827</EditorX><EditorY>649</EditorY><m_Algorithm i:type="AlgorithmBeingsComplete" z:Id="i99" /><m_Layers z:Id="i100"><StorageLayer z:Ref="i95" /></m_Layers></StorageLayer><StorageLayer z:Id="i101"><EditorX>1051</EditorX><EditorY>354</EditorY><m_Algorithm i:type="AlgorithmFormResult" z:Id="i102" /><m_Layers z:Id="i103"><StorageLayer z:Ref="i44" /><StorageLayer z:Ref="i47" /><StorageLayer z:Ref="i80" /><StorageLayer z:Ref="i98" /></m_Layers></StorageLayer></ArrayOfStorageLayer>